LICENSE
MANIFEST.in
README.rst
setup.py
scripts/spilleliste
spilleliste/__init__.py
spilleliste/core.py
spilleliste/generator.py
spilleliste.egg-info/PKG-INFO
spilleliste.egg-info/SOURCES.txt
spilleliste.egg-info/dependency_links.txt
spilleliste.egg-info/requires.txt
spilleliste.egg-info/top_level.txt
spilleliste/connectors/__init__.py
spilleliste/connectors/googlemusic.py
spilleliste/connectors/itunes.py
spilleliste/externals/__init__.py
spilleliste/externals/googleimage.py
spilleliste/externals/spotify.py
spilleliste/externals/youtube.py