Metadata-Version: 1.1
Name: spilleliste
Version: 0.1.2
Summary: Spilleliste, share your beautiful playlist.
Home-page: https://github.com/toxinu/spilleliste
Author: toxinu
Author-email: toxinu@gmail.com
License: Copyright (c) 2013, toxinu
